mypackagesocool22072022/__init__.py
mypackagesocool22072022/add_one.py
mypackagesocool22072022/my_math.py
mypackagesocool22072022-1.1.dist-info/METADATA
mypackagesocool22072022-1.1.dist-info/WHEEL
mypackagesocool22072022-1.1.dist-info/top_level.txt
mypackagesocool22072022-1.1.dist-info/RECORD
