Metadata-Version: 2.1
Name: mypackagesocool22072022
Version: 1.1
Summary: this package really cool
Home-page: UNKNOWN
License: UNKNOWN
Platform: UNKNOWN
